part_2/reg16_8.vhd
library IEEE;
use IEEE.STD_LOGIC_1164.all;
use IEEE.NUMERIC_STD.all;

entity reg16_8 is

  port (
    clk    : in  std_logic;
    en     : in  std_logic;
    data_d : in  std_logic_vector(15 downto 0);
    data_a : out std_logic_vector(15 downto 0);
    data_b : out std_logic_vector(15 downto 0);
    sel_a  : in  std_logic_vector(2 downto 0);
    sel_b  : in  std_logic_vector(2 downto 0);
    sel_d  : in  std_logic_vector(2 downto 0);
    we     : in  std_logic);
end entity reg16_8;

architecture rtl of reg16_8 is

  type store_t is array (0 to 7) of std_logic_vector(15 downto 0);
  signal regs : store_t := (others => X"0000");

begin

  process (clk) is
  begin

    if rising_edge(clk) and en = '1' then
      data_a <= regs(to_integer(unsigned(sel_a)));
      data_b <= regs(to_integer(unsigned(sel_b)));
      if we = '1' then
        regs(to_integer(unsigned(sel_d))) <= data_d;
      end if;
    end if;
  end process;
end architecture rtl;

part_2/tb_reg16_8.vhd
library IEEE;
use IEEE.std_logic_1164.all;

entity tb_reg16_8 is
end entity tb_reg16_8;

architecture behav of tb_reg16_8 is

  component reg16_8 is
    port (
      clk    : in  std_logic;
      en     : in  std_logic;
      data_d : in  std_logic_vector(15 downto 0);
      data_a : out std_logic_vector(15 downto 0);
      data_b : out std_logic_vector(15 downto 0);
      sel_a  : in  std_logic_vector(2 downto 0);
      sel_b  : in  std_logic_vector(2 downto 0);
      sel_d  : in  std_logic_vector(2 downto 0);
      we     : in  std_logic);
  end component reg16_8;

  signal clk    : std_logic                     := '0';
  signal en     : std_logic                     := '0';
  signal data_d : std_logic_vector(15 downto 0) := (others => '0');
  signal sel_a  : std_logic_vector(2 downto 0)  := (others => '0');
  signal sel_b  : std_logic_vector(2 downto 0)  := (others => '0');
  signal sel_d  : std_logic_vector(2 downto 0)  := (others => '0');
  signal we     : std_logic                     := '0';

  signal data_a : std_logic_vector(15 downto 0);
  signal data_b : std_logic_vector(15 downto 0);

  constant CLK_PERIOD : time := 10 ns;

begin

  uut : reg16_8 port map (
    clk    => clk,
    en     => en,
    data_d => data_d,
    data_a => data_a,
    data_b => data_b,
    sel_a  => sel_a,
    sel_b  => sel_b,
    sel_d  => sel_d,
    we     => we
    );

  clk_process : process
  begin
    clk <= '0';
    wait for clk_period/2;
    clk <= '1';
    wait for clk_period/2;
  end process;

  stimulate : process
  begin
    wait for 100 ns;
    wait for clk_period*10;

    en <= '1';

    -- test for writing.
    -- r0 = 0xfab5
    sel_a  <= "000";
    sel_b  <= "001";
    sel_d  <= "000";
    data_d <= X"FAB5";
    we     <= '1';
    wait for clk_period;

    -- r2 = 0x2222
    sel_a  <= "000";
    sel_b  <= "001";
    sel_d  <= "010";
    data_d <= X"2222";
    we     <= '1';
    wait for clk_period;

    -- r3 = 0x3333
    sel_a  <= "000";
    sel_b  <= "001";
    sel_d  <= "010";
    data_d <= X"3333";
    we     <= '1';
    wait for clk_period;

    --test just reading, with no write
    sel_a  <= "000";
    sel_b  <= "001";
    sel_d  <= "000";
    data_d <= X"FEED";
    we     <= '0';
    wait for clk_period;

    --at this point dataA should not be 'feed'

    sel_a <= "001";
    sel_b <= "010";
    wait for clk_period;

    sel_a <= "011";
    sel_b <= "100";
    wait for clk_period;

    sel_a  <= "000";
    sel_b  <= "001";
    sel_d  <= "100";
    data_d <= X"4444";
    we     <= '1';
    wait for clk_period;

    we <= '0';
    wait for clk_period;

    -- nop
    wait for clk_period;

    sel_a <= "100";
    sel_b <= "100";
    wait for clk_period;

    assert false report "Sim Finished" severity failure;
  end process;
end architecture behav;

part_2/reg16_8.vcd
$date
  Thu Nov 22 21:27:01 2018
$end
$version
  GHDL v0
$end
$timescale
  1 fs
$end
$scope module standard $end
$upscope $end
$scope module std_logic_1164 $end
$upscope $end
$scope module numeric_std $end
$upscope $end
$scope module tb_reg16_8 $end
$var reg 1 ! clk $end
$var reg 1 " en $end
$var reg 16 # data_d[15:0] $end
$var reg 3 $ sel_a[2:0] $end
$var reg 3 % sel_b[2:0] $end
$var reg 3 & sel_d[2:0] $end
$var reg 1 ' we $end
$var reg 16 ( data_a[15:0] $end
$var reg 16 ) data_b[15:0] $end
$scope module uut $end
$var reg 1 * clk $end
$var reg 1 + en $end
$var reg 16 , data_d[15:0] $end
$var reg 16 - data_a[15:0] $end
$var reg 16 . data_b[15:0] $end
$var reg 3 / sel_a[2:0] $end
$var reg 3 0 sel_b[2:0] $end
$var reg 3 1 sel_d[2:0] $end
$var reg 1 2 we $end
$comment regs is not handled $end
$upscope $end
$upscope $end
$enddefinitions $end
#0
0!
0"
b0000000000000000 #
b000 $
b000 %
b000 &
0'
bUUUUUUUUUUUUUUUU (
bUUUUUUUUUUUUUUUU )
0*
0+
b0000000000000000 ,
bUUUUUUUUUUUUUUUU -
bUUUUUUUUUUUUUUUU .
b000 /
b000 0
b000 1
02
#5000000
1!
1*
#10000000
0!
0*
#15000000
1!
1*
#20000000
0!
0*
#25000000
1!
1*
#30000000
0!
0*
#35000000
1!
1*
#40000000
0!
0*
#45000000
1!
1*
#50000000
0!
0*
#55000000
1!
1*
#60000000
0!
0*
#65000000
1!
1*
#70000000
0!
0*
#75000000
1!
1*
#80000000
0!
0*
#85000000
1!
1*
#90000000
0!
0*
#95000000
1!
1*
#100000000
0!
0*
#105000000
1!
1*
#110000000
0!
0*
#115000000
1!
1*
#120000000
0!
0*
#125000000
1!
1*
#130000000
0!
0*
#135000000
1!
1*
#140000000
0!
0*
#145000000
1!
1*
#150000000
0!
0*
#155000000
1!
1*
#160000000
0!
0*
#165000000
1!
1*
#170000000
0!
0*
#175000000
1!
1*
#180000000
0!
0*
#185000000
1!
1*
#190000000
0!
0*
#195000000
1!
1*
#200000000
0!
1"
b1111101010110101 #
b001 %
1'
0*
1+
b1111101010110101 ,
b001 0
12
#205000000
1!
b0000000000000000 (
b0000000000000000 )
1*
b0000000000000000 -
b0000000000000000 .
#210000000
0!
b0010001000100010 #
b010 &
0*
b0010001000100010 ,
b010 1
#215000000
1!
b1111101010110101 (
1*
b1111101010110101 -
#220000000
0!
b0011001100110011 #
0*
b0011001100110011 ,
#225000000
1!
1*
#230000000
0!
b1111111011101101 #
b000 &
0'
0*
b1111111011101101 ,
b000 1
02
#235000000
1!
1*
#240000000
0!
b001 $
b010 %
0*
b001 /
b010 0
#245000000
1!
b0000000000000000 (
b0011001100110011 )
1*
b0000000000000000 -
b0011001100110011 .
#250000000
0!
b011 $
b100 %
0*
b011 /
b100 0
#255000000
1!
b0000000000000000 )
1*
b0000000000000000 .
#260000000
0!
b0100010001000100 #
b000 $
b001 %
b100 &
1'
0*
b0100010001000100 ,
b000 /
b001 0
b100 1
12
#265000000
1!
b1111101010110101 (
1*
b1111101010110101 -
#270000000
0!
0'
0*
02
#275000000
1!
1*
#280000000
0!
0*
#285000000
1!
1*
#290000000
0!
b100 $
b100 %
0*
b100 /
b100 0
#295000000
1!
b0100010001000100 (
b0100010001000100 )
1*
b0100010001000100 -
b0100010001000100 .
